cli/README.md
cli/__init__.py
cli/api_client.py
cli/auth_resolver.py
cli/config.py
cli/http_executor.py
cli/main.py
cli/models.py
cli/reporters.py
cli/scenario_executor.py
smarttest_cli-0.1.3.dist-info/licenses/LICENSE
smarttest_cli-0.1.3.dist-info/METADATA
smarttest_cli-0.1.3.dist-info/WHEEL
smarttest_cli-0.1.3.dist-info/entry_points.txt
smarttest_cli-0.1.3.dist-info/top_level.txt
smarttest_cli-0.1.3.dist-info/RECORD
