Metadata-Version: 2.4
Name: smarttest-cli
Version: 0.1.3
Summary: SmartTest CLI - Execute test scenarios with secure credential handling
Author-email: SmartTest Team <ai.smart.test.contact@gmail.com>
Maintainer-email: SmartTest Team <ai.smart.test.contact@gmail.com>
License: MIT
Project-URL: Homepage, https://ai-smart-test.vercel.app/
Project-URL: Documentation, https://ai-smart-test.vercel.app/docs
Project-URL: Repository, https://github.com/smarttest/smarttest-cli
Project-URL: Bug Tracker, https://github.com/smarttest/smarttest-cli/issues
Keywords: testing,api,cli,automation,ci-cd,continuous-integration,api-testing
Classifier: Development Status :: 4 - Beta
Classifier: Intended Audience :: Developers
Classifier: License :: OSI Approved :: MIT License
Classifier: Operating System :: OS Independent
Classifier: Programming Language :: Python :: 3
Classifier: Programming Language :: Python :: 3.8
Classifier: Programming Language :: Python :: 3.9
Classifier: Programming Language :: Python :: 3.10
Classifier: Programming Language :: Python :: 3.11
Classifier: Programming Language :: Python :: 3.12
Classifier: Topic :: Software Development :: Testing
Classifier: Topic :: Software Development :: Quality Assurance
Requires-Python: >=3.8
License-File: LICENSE
Requires-Dist: typer>=0.9.0
Requires-Dist: httpx>=0.24.0
Requires-Dist: rich>=13.0.0
Requires-Dist: pyyaml>=6.0
Requires-Dist: pydantic>=2.0.0
Provides-Extra: dev
Requires-Dist: pytest>=7.0.0; extra == "dev"
Requires-Dist: pytest-asyncio>=0.21.0; extra == "dev"
Requires-Dist: pytest-mock>=3.10.0; extra == "dev"
Dynamic: license-file
